toile/__init__.py
toile/__main__.py
toile/_common.py
toile/export.py
toile/schema.py
toile/tiff_import.py
toile-0.1.1a2.dist-info/METADATA
toile-0.1.1a2.dist-info/WHEEL
toile-0.1.1a2.dist-info/entry_points.txt
toile-0.1.1a2.dist-info/licenses/LICENSE
toile-0.1.1a2.dist-info/RECORD
