Metadata-Version: 2.4
Name: toile
Version: 0.1.1a2
Summary: Tools for working with astrocyte dynamics data
Author-email: Maxine Levesque <220467675+maxine-at-forecast@users.noreply.github.com>
License-File: LICENSE
Requires-Python: >=3.12
Requires-Dist: atdata>=0.1.1a2
Requires-Dist: scikit-image>=0.25.2
Requires-Dist: typer>=0.20.0
Requires-Dist: xmltodict>=1.0.2
